lobrow/__init__.py
lobrow/__main__.py
lobrow/command/__init__.py
lobrow/command/start_command.py
lobrow-0.0.2.dist-info/METADATA
lobrow-0.0.2.dist-info/WHEEL
lobrow-0.0.2.dist-info/entry_points.txt
lobrow-0.0.2.dist-info/RECORD
