Metadata-Version: 2.1
Name: lobrow
Version: 0.0.2
Summary: Browse local files with a local server. Read documentation on an airplane.
License: MIT
Author: Steampunk Wizard
Author-email: lobrow@steampunkwizard.ca
Requires-Python: >=3.11,<3.12
Classifier: License :: OSI Approved :: MIT License
Classifier: Programming Language :: Python :: 3
Classifier: Programming Language :: Python :: 3.11
Requires-Dist: wizlib (>=2.0.5,<3.0.0)
